pysh/__init__.py
pysh/pysh.py
pysh/token_transformers.py
pysh/util.py
pysh_stub-1.1.4.dist-info/entry_points.txt
pysh_stub-1.1.4.dist-info/LICENSE.txt
pysh_stub-1.1.4.dist-info/WHEEL
pysh_stub-1.1.4.dist-info/METADATA
pysh_stub-1.1.4.dist-info/RECORD
